[
  {
    "id": "devfolio-0-1750400641333",
    "title": "Chromion: A Chainlink Hackathon",
    "desc": "Hackathon",
    "date": "Check website for dates",
    "mode": "Online",
    "location": "India",
    "sectorTags": [
      "Technology"
    ],
    "organiser": "Devfolio",
    "link": "https://chromion-chainlink-hackathon.devfolio.co/"
  },
  {
    "id": "devfolio-1-1750400641334",
    "title": "Coinbase Agents in Action Hackathon",
    "desc": "Hackathon",
    "date": "Check website for dates",
    "mode": "Online",
    "location": "India",
    "sectorTags": [
      "Technology"
    ],
    "organiser": "Devfolio",
    "link": "https://cdp-agentkit-hackathon.devfolio.co/"
  },
  {
    "id": "devfolio-2-1750400641335",
    "title": "Base Batch Messaging Buildathon",
    "desc": "Hackathon",
    "date": "Check website for dates",
    "mode": "Online",
    "location": "India",
    "sectorTags": [
      "Technology"
    ],
    "organiser": "Devfolio",
    "link": "https://base-batch-messaging.devfolio.co/"
  },
  {
    "id": "devfolio-3-1750400641335",
    "title": "Warpspeed: Agentic AI Hackathon | Lightspeed India",
    "desc": "Hackathon",
    "date": "Check website for dates",
    "mode": "Online",
    "location": "India",
    "sectorTags": [
      "Technology"
    ],
    "organiser": "Devfolio",
    "link": "https://warpspeed2025.devfolio.co/"
  },
  {
    "id": "devfolio-4-1750400641336",
    "title": "Chromion: A Chainlink Hackathon",
    "desc": "Hackathon",
    "date": "Check website for dates",
    "mode": "Online",
    "location": "India",
    "sectorTags": [
      "Technology"
    ],
    "organiser": "Devfolio",
    "link": "https://chromion-chainlink-hackathon.devfolio.co/"
  },
  {
    "id": "devfolio-5-1750400641336",
    "title": "Coinbase Agents in Action Hackathon",
    "desc": "Hackathon",
    "date": "Check website for dates",
    "mode": "Online",
    "location": "India",
    "sectorTags": [
      "Technology"
    ],
    "organiser": "Devfolio",
    "link": "https://cdp-agentkit-hackathon.devfolio.co/"
  },
  {
    "id": "devfolio-6-1750400641337",
    "title": "Base Batch Messaging Buildathon",
    "desc": "Hackathon",
    "date": "Check website for dates",
    "mode": "Online",
    "location": "India",
    "sectorTags": [
      "Technology"
    ],
    "organiser": "Devfolio",
    "link": "https://base-batch-messaging.devfolio.co/"
  },
  {
    "id": "devfolio-7-1750400641337",
    "title": "Warpspeed: Agentic AI Hackathon | Lightspeed India",
    "desc": "Hackathon",
    "date": "Check website for dates",
    "mode": "Online",
    "location": "India",
    "sectorTags": [
      "Technology"
    ],
    "organiser": "Devfolio",
    "link": "https://warpspeed2025.devfolio.co/"
  },
  {
    "id": "devfolio-8-1750400641338",
    "title": "HackArenaa",
    "desc": "Hackathon",
    "date": "Check website for dates",
    "mode": "Online",
    "location": "India",
    "sectorTags": [
      "Technology"
    ],
    "organiser": "Devfolio",
    "link": "https://hackarenaa.devfolio.co/"
  },
  {
    "id": "devfolio-9-1750400641339",
    "title": "ZK Hack Berlin",
    "desc": "Hackathon",
    "date": "Check website for dates",
    "mode": "Online",
    "location": "India",
    "sectorTags": [
      "Technology"
    ],
    "organiser": "Devfolio",
    "link": "https://zk-hack-berlin.devfolio.co/"
  },
  {
    "id": "devfolio-10-1750400641340",
    "title": "Coinbase Agents in Action Hackathon",
    "desc": "Hackathon",
    "date": "Check website for dates",
    "mode": "Online",
    "location": "India",
    "sectorTags": [
      "Technology"
    ],
    "organiser": "Devfolio",
    "link": "https://cdp-agentkit-hackathon.devfolio.co/"
  },
  {
    "id": "devfolio-11-1750400641340",
    "title": "Chromion: A Chainlink Hackathon",
    "desc": "Hackathon",
    "date": "Check website for dates",
    "mode": "Online",
    "location": "India",
    "sectorTags": [
      "Technology"
    ],
    "organiser": "Devfolio",
    "link": "https://chromion-chainlink-hackathon.devfolio.co/"
  },
  {
    "id": "devfolio-12-1750400641341",
    "title": "The IndeHub Hackathon | Build With WWDC25",
    "desc": "Hackathon",
    "date": "Check website for dates",
    "mode": "Online",
    "location": "India",
    "sectorTags": [
      "Technology"
    ],
    "organiser": "Devfolio",
    "link": "https://wwdc25.devfolio.co/"
  },
  {
    "id": "devfolio-13-1750400641342",
    "title": "Hack Quanta",
    "desc": "Hackathon",
    "date": "Check website for dates",
    "mode": "Online",
    "location": "India",
    "sectorTags": [
      "Technology"
    ],
    "organiser": "Devfolio",
    "link": "https://hack-quanta.devfolio.co/"
  },
  {
    "id": "devfolio-14-1750400641343",
    "title": "Hacking Paris  | Powered by Chiliz",
    "desc": "Hackathon",
    "date": "Check website for dates",
    "mode": "Online",
    "location": "India",
    "sectorTags": [
      "Technology"
    ],
    "organiser": "Devfolio",
    "link": "https://hacking-paris.devfolio.co/"
  },
  {
    "id": "devfolio-15-1750400641343",
    "title": "Metis Hyperion: HyperHack",
    "desc": "Hackathon",
    "date": "Check website for dates",
    "mode": "Online",
    "location": "India",
    "sectorTags": [
      "Technology"
    ],
    "organiser": "Devfolio",
    "link": "https://metis-hyperhack.devfolio.co/"
  },
  {
    "id": "devfolio-16-1750400641344",
    "title": ".hack(); 25",
    "desc": "Hackathon",
    "date": "Check website for dates",
    "mode": "Online",
    "location": "India",
    "sectorTags": [
      "Technology"
    ],
    "organiser": "Devfolio",
    "link": "https://hack25.devfolio.co/"
  },
  {
    "id": "devfolio-17-1750400641345",
    "title": "DEVMatch Hackathon 2025",
    "desc": "Hackathon",
    "date": "Check website for dates",
    "mode": "Online",
    "location": "India",
    "sectorTags": [
      "Technology"
    ],
    "organiser": "Devfolio",
    "link": "https://devmatch-hackathon.devfolio.co/"
  },
  {
    "id": "devfolio-18-1750400641345",
    "title": "Hack4Maharashtra",
    "desc": "Hackathon",
    "date": "Check website for dates",
    "mode": "Online",
    "location": "India",
    "sectorTags": [
      "Technology"
    ],
    "organiser": "Devfolio",
    "link": "https://hack4maharashtra.devfolio.co/"
  },
  {
    "id": "devfolio-19-1750400641346",
    "title": "Lisk Builders Challenge: Round Two",
    "desc": "Hackathon",
    "date": "Check website for dates",
    "mode": "Online",
    "location": "India",
    "sectorTags": [
      "Technology"
    ],
    "organiser": "Devfolio",
    "link": "https://lisk-builders-challenge-2.devfolio.co/"
  },
  {
    "id": "devfolio-20-1750400641346",
    "title": "Hack The Horizon 2.0 (VIT-Chennai)",
    "desc": "Hackathon",
    "date": "Check website for dates",
    "mode": "Online",
    "location": "India",
    "sectorTags": [
      "Technology"
    ],
    "organiser": "Devfolio",
    "link": "https://hack-the-horizon-2.devfolio.co/"
  },
  {
    "id": "devfolio-21-1750400641346",
    "title": "StatusCode 2",
    "desc": "Hackathon",
    "date": "Check website for dates",
    "mode": "Online",
    "location": "India",
    "sectorTags": [
      "Technology"
    ],
    "organiser": "Devfolio",
    "link": "https://statuscode-2.devfolio.co/"
  },
  {
    "id": "devfolio-22-1750400641347",
    "title": "Hack4Brahmaputra",
    "desc": "Hackathon",
    "date": "Check website for dates",
    "mode": "Online",
    "location": "India",
    "sectorTags": [
      "Technology"
    ],
    "organiser": "Devfolio",
    "link": "https://hack4brahmaputra.devfolio.co/"
  },
  {
    "id": "devfolio-23-1750400641347",
    "title": "Hack-O-Knight",
    "desc": "Hackathon",
    "date": "Check website for dates",
    "mode": "Online",
    "location": "India",
    "sectorTags": [
      "Technology"
    ],
    "organiser": "Devfolio",
    "link": "https://hack-o-knight.devfolio.co/"
  },
  {
    "id": "devfolio-24-1750400641347",
    "title": "RNS Hack_Overflow 2.0",
    "desc": "Hackathon",
    "date": "Check website for dates",
    "mode": "Online",
    "location": "India",
    "sectorTags": [
      "Technology"
    ],
    "organiser": "Devfolio",
    "link": "https://rns-hackoverflow-2.devfolio.co/"
  },
  {
    "id": "devfolio-25-1750400641348",
    "title": "DevShastra",
    "desc": "Hackathon",
    "date": "Check website for dates",
    "mode": "Online",
    "location": "India",
    "sectorTags": [
      "Technology"
    ],
    "organiser": "Devfolio",
    "link": "https://devshastracodechef.devfolio.co/"
  },
  {
    "id": "devfolio-26-1750400641348",
    "title": "HackPrix Season 2",
    "desc": "Hackathon",
    "date": "Check website for dates",
    "mode": "Online",
    "location": "India",
    "sectorTags": [
      "Technology"
    ],
    "organiser": "Devfolio",
    "link": "https://hackprix-2025.devfolio.co/"
  },
  {
    "id": "devfolio-27-1750400641348",
    "title": "ETHKyiv 2025",
    "desc": "Hackathon",
    "date": "Check website for dates",
    "mode": "Online",
    "location": "India",
    "sectorTags": [
      "Technology"
    ],
    "organiser": "Devfolio",
    "link": "https://ethkyiv.devfolio.co/"
  },
  {
    "id": "devfolio-28-1750400641349",
    "title": "Base Batch Messaging Buildathon",
    "desc": "Hackathon",
    "date": "Check website for dates",
    "mode": "Online",
    "location": "India",
    "sectorTags": [
      "Technology"
    ],
    "organiser": "Devfolio",
    "link": "https://base-batch-messaging.devfolio.co/"
  }
]
